{
  "source_file": "articles_flat.jsonl",
  "num_articles_scanned": 830,
  "results": {
    "BRICS": {
      "count": 17,
      "ids": [
        "art_000002",
        "art_000003",
        "art_000026",
        "art_000076",
        "art_000147",
        "art_000153",
        "art_000155",
        "art_000223",
        "art_000225",
        "art_000240",
        "art_000266",
        "art_000271",
        "art_000283",
        "art_000349",
        "art_000384",
        "art_000608",
        "art_000632"
      ]
    },
    "BRI_Belt_and_Road": {
      "count": 65,
      "ids": [
        "art_000003",
        "art_000026",
        "art_000076",
        "art_000083",
        "art_000091",
        "art_000101",
        "art_000125",
        "art_000131",
        "art_000145",
        "art_000147",
        "art_000152",
        "art_000155",
        "art_000191",
        "art_000200",
        "art_000202",
        "art_000208",
        "art_000215",
        "art_000217",
        "art_000224",
        "art_000225",
        "art_000233",
        "art_000239",
        "art_000240",
        "art_000242",
        "art_000256",
        "art_000265",
        "art_000266",
        "art_000271",
        "art_000272",
        "art_000273",
        "art_000277",
        "art_000279",
        "art_000281",
        "art_000283",
        "art_000313",
        "art_000316",
        "art_000319",
        "art_000338",
        "art_000346",
        "art_000349",
        "art_000355",
        "art_000360",
        "art_000366",
        "art_000369",
        "art_000375",
        "art_000384",
        "art_000385",
        "art_000386",
        "art_000544",
        "art_000608",
        "art_000652",
        "art_000653",
        "art_000668",
        "art_000688",
        "art_000690",
        "art_000702",
        "art_000708",
        "art_000732",
        "art_000735",
        "art_000740",
        "art_000757",
        "art_000760",
        "art_000782",
        "art_000794",
        "art_000795"
      ]
    },
    "SCO_Shanghai_Cooperation_Organization": {
      "count": 57,
      "ids": [
        "art_000008",
        "art_000026",
        "art_000033",
        "art_000044",
        "art_000048",
        "art_000054",
        "art_000057",
        "art_000076",
        "art_000080",
        "art_000085",
        "art_000102",
        "art_000105",
        "art_000152",
        "art_000191",
        "art_000203",
        "art_000207",
        "art_000226",
        "art_000241",
        "art_000257",
        "art_000263",
        "art_000268",
        "art_000274",
        "art_000278",
        "art_000280",
        "art_000302",
        "art_000303",
        "art_000321",
        "art_000322",
        "art_000343",
        "art_000350",
        "art_000353",
        "art_000357",
        "art_000363",
        "art_000381",
        "art_000385",
        "art_000394",
        "art_000404",
        "art_000421",
        "art_000436",
        "art_000553",
        "art_000559",
        "art_000567",
        "art_000586",
        "art_000607",
        "art_000624",
        "art_000652",
        "art_000666",
        "art_000680",
        "art_000702",
        "art_000709",
        "art_000711",
        "art_000713",
        "art_000716",
        "art_000761",
        "art_000776",
        "art_000792",
        "art_000808"
      ]
    },
    "NATO": {
      "count": 57,
      "ids": [
        "art_000017",
        "art_000027",
        "art_000071",
        "art_000096",
        "art_000138",
        "art_000188",
        "art_000196",
        "art_000297",
        "art_000314",
        "art_000318",
        "art_000334",
        "art_000363",
        "art_000399",
        "art_000403",
        "art_000415",
        "art_000421",
        "art_000427",
        "art_000429",
        "art_000432",
        "art_000436",
        "art_000450",
        "art_000453",
        "art_000467",
        "art_000486",
        "art_000493",
        "art_000504",
        "art_000505",
        "art_000507",
        "art_000512",
        "art_000514",
        "art_000519",
        "art_000524",
        "art_000540",
        "art_000558",
        "art_000563",
        "art_000570",
        "art_000591",
        "art_000601",
        "art_000626",
        "art_000636",
        "art_000639",
        "art_000642",
        "art_000650",
        "art_000675",
        "art_000679",
        "art_000690",
        "art_000700",
        "art_000703",
        "art_000705",
        "art_000726",
        "art_000728",
        "art_000738",
        "art_000743",
        "art_000744",
        "art_000761",
        "art_000764",
        "art_000765"
      ]
    },
    "Ukraine": {
      "count": 85,
      "ids": [
        "art_000021",
        "art_000026",
        "art_000027",
        "art_000100",
        "art_000124",
        "art_000179",
        "art_000181",
        "art_000183",
        "art_000187",
        "art_000188",
        "art_000189",
        "art_000192",
        "art_000193",
        "art_000194",
        "art_000195",
        "art_000197",
        "art_000198",
        "art_000204",
        "art_000219",
        "art_000224",
        "art_000227",
        "art_000234",
        "art_000236",
        "art_000252",
        "art_000253",
        "art_000254",
        "art_000262",
        "art_000269",
        "art_000275",
        "art_000297",
        "art_000334",
        "art_000378",
        "art_000387",
        "art_000388",
        "art_000392",
        "art_000400",
        "art_000401",
        "art_000402",
        "art_000405",
        "art_000412",
        "art_000415",
        "art_000416",
        "art_000424",
        "art_000425",
        "art_000432",
        "art_000440",
        "art_000441",
        "art_000453",
        "art_000479",
        "art_000502",
        "art_000517",
        "art_000556",
        "art_000570",
        "art_000572",
        "art_000596",
        "art_000597",
        "art_000599",
        "art_000616",
        "art_000617",
        "art_000620",
        "art_000640",
        "art_000642",
        "art_000646",
        "art_000648",
        "art_000651",
        "art_000653",
        "art_000664",
        "art_000669",
        "art_000675",
        "art_000685",
        "art_000690",
        "art_000695",
        "art_000696",
        "art_000712",
        "art_000733",
        "art_000736",
        "art_000738",
        "art_000743",
        "art_000754",
        "art_000764",
        "art_000769",
        "art_000774",
        "art_000780",
        "art_000781",
        "art_000794"
      ]
    },
    "Artificial_Intelligence": {
      "count": 1,
      "ids": [
        "art_000171"
      ]
    },
    "Finland": {
      "count": 1,
      "ids": [
        "art_000642"
      ]
    }
  }
}